{"_id":{"$oid":"5af50ff5c082f1e92f834264"},"title":"Movie Reviews 1 ","author":{"$oid":"5af50c84c082f1e92f83420b"},"content":"Blade Runner 2049","comments":[{"content":"Awesome"},{"content":"Cerebral"},{"content":"Confusing"},{"content":"Two Thumbs Up!"}]}
{"_id":{"$oid":"5af50ff5c082f1e92f834265"},"title":"Movie Reviews 2","author":{"$oid":"5af50c84c082f1e92f834209"},"content":"Inception","comments":[]}
{"_id":{"$oid":"5af50ff5c082f1e92f834266"},"title":"Movie Reviews 3 ","author":{"$oid":"5af50c84c082f1e92f834209"},"content":"Interstellar","comments":[{"content":"Weird"},{"content":"Kinda Long"},{"content":"Provocative"},{"content":"Good"}]}
{"_id":{"$oid":"5af50ff5c082f1e92f834268"},"title":"Movie Reviews 4","author":{"$oid":"5af50c84c082f1e92f83420a"},"content":"Eternal Sunshine of the Spotless Mind ","comments":[{"content":"Really"},{"content":"Duuude"},{"content":"Evocative"},{"content":"it was ok"}]}
{"_id":{"$oid":"5af50ff5c082f1e92f834269"},"title":"Movie Reviews 5","author":{"$oid":"5af50c84c082f1e92f834209"},"content":"V for Vendetta","comments":[{"content":"I loved it"},{"content":"Yep, good."},{"content":"WTF!"},{"content":"Yea Buddy"}]}
{"_id":{"$oid":"5af50ff5c082f1e92f83426a"},"title":"Movie Reviews 6","author":{"$oid":"5af50c84c082f1e92f83420a"},"content":"Mad Max: Fury Road","comments":[]}
{"_id":{"$oid":"5af50ff5c082f1e92f83426b"},"title":"Movie Reviews 7","author":{"$oid":"5af50c84c082f1e92f83420a"},"content":"The Martian","comments":[]}
{"_id":{"$oid":"5af50ff5c082f1e92f83426c"},"title":"Movie Reviews 8","author":{"$oid":"5af50c84c082f1e92f83420c"},"content":"Her","comments":[{"content":"I'll watch it again"},{"content":"Really Good"},{"content":"Timeless"},{"content":"oh yea brother"}]}
{"_id":{"$oid":"5af50ff5c082f1e92f83426d"},"title":"Movie Reviews 9","author":{"$oid":"5af50c84c082f1e92f83420c"},"content":"Star Trek","comments":[{"content":"whoaa"},{"content":"Daanng"},{"content":"Oh yea"}]}
{"_id":{"$oid":"5af50ff5c082f1e92f83426e"},"title":"Movie Reviews 10","author":{"$oid":"5af50c84c082f1e92f834209"},"content":"Edge of Tomorrow","comments":[{"content":"wha?!"},{"content":"what was this?!"}]}